README.rst
setup.cfg
setup.py
asynctmdb/__init__.py
asynctmdb/common.py
asynctmdb/config.py
asynctmdb/requests.py
asynctmdb/types.py
asynctmdb/utils.py
asynctmdb.egg-info/PKG-INFO
asynctmdb.egg-info/SOURCES.txt
asynctmdb.egg-info/dependency_links.txt
asynctmdb.egg-info/requires.txt
asynctmdb.egg-info/top_level.txt
asynctmdb/imdb/__init__.py
asynctmdb/imdb/find.py
asynctmdb/imdb/title_id.py
asynctmdb/methods/__init__.py
asynctmdb/methods/authentication.py
asynctmdb/methods/find.py
asynctmdb/methods/genres.py
asynctmdb/methods/movies.py
tests/fixtures/__init__.py
tests/fixtures/api.py
tests/fixtures/authentication.py
tests/fixtures/imdb.py
tests/fixtures/movies.py
tests/fixtures/session.py
tests/fixtures/utils.py
tests/imdb_tests/__init__.py
tests/imdb_tests/test_find.py
tests/methods_tests/__init__.py
tests/methods_tests/test_authentication.py
tests/methods_tests/test_genres.py
tests/methods_tests/test_movies.py
tests/strategies/__init__.py
tests/strategies/api.py
tests/strategies/authentication.py
tests/strategies/imdb.py
tests/strategies/movies.py
tests/strategies/utils.py