Metadata-Version: 1.1
Name: asynctmdb
Version: 0.0.2
Summary: Asynchronous working with TMDB API.
Home-page: https://github.com/lycantropos/asynctmdb
Author: Azat Ibrakov
Author-email: azatibrakov@gmail.com
License: MIT
Download-URL: https://github.com/lycantropos/asynctmdb/archive/master.tar.gz
Platform: UNKNOWN
Classifier: Development Status :: 3 - Alpha
Classifier: Environment :: Web Environment
Classifier: Framework :: AsyncIO
Classifier: Intended Audience :: Developers
Classifier: License :: OSI Approved :: MIT License
Classifier: Programming Language :: Python :: 3.5
Classifier: Programming Language :: Python :: 3.6
Classifier: Programming Language :: Python :: Implementation :: CPython
Classifier: Operating System :: POSIX
Classifier: Operating System :: MacOS :: MacOS X
Classifier: Operating System :: Microsoft :: Windows
Classifier: Topic :: Internet :: WWW/HTTP
